ml_derivatives/__init__.py
ml_derivatives/mld.py
ml_derivatives/data/.DS_Store
ml_derivatives/data/Ma_0.01_50.pkl
ml_derivatives/data/Ma_0.025_50.pkl
ml_derivatives/data/Ma_0.05_50.pkl
ml_derivatives/data/Ma_0.08_50.pkl
ml_derivatives/data/Ma_0.1_50.pkl
ml_derivatives-0.0.2.dist-info/LICENSE
ml_derivatives-0.0.2.dist-info/METADATA
ml_derivatives-0.0.2.dist-info/WHEEL
ml_derivatives-0.0.2.dist-info/top_level.txt
ml_derivatives-0.0.2.dist-info/RECORD
